nexadataset/__init__.py
nexadataset/config.py
nexadataset/settings.py
nexadataset/cli/__init__.py
nexadataset/cli/download.py
nexadataset/cli/main.py
nexadataset/dataset/__init__.py
nexadataset/dataset/client.py
nexadataset/error/__init__.py
nexadataset/error/download_exception.py
nexadataset/error/error_code.py
nexadataset/services/__init__.py
nexadataset/services/auth.py
nexadataset/services/dataset_info.py
nexadataset/services/download_service.py
nexadataset/services/models.py
nexadataset-0.1.1.dist-info/METADATA
nexadataset-0.1.1.dist-info/WHEEL
nexadataset-0.1.1.dist-info/entry_points.txt
nexadataset-0.1.1.dist-info/top_level.txt
nexadataset-0.1.1.dist-info/RECORD
