Metadata-Version: 2.4
Name: nexadataset
Version: 0.1.1
Summary: 数据集管理平台SDK
Author-email: shimingming <shimingming@zoneyet.com>
License: MIT
Project-URL: Homepage, http://172.16.1.35/shimingming/nexadataset-sdk
Keywords: nexa,dataset,sdk,async,download
Classifier: Programming Language :: Python :: 3
Classifier: License :: OSI Approved :: MIT License
Classifier: Operating System :: OS Independent
Requires-Python: >=3.10
Requires-Dist: setuptools~=75.8.0
Requires-Dist: pyjwt~=2.10.1
Requires-Dist: httpx~=0.27.0
Requires-Dist: aiofiles~=22.1.0
Requires-Dist: pydantic~=2.11.1
Requires-Dist: tenacity~=9.0.0
Requires-Dist: tqdm~=4.67.1
Requires-Dist: click~=8.1.7
Requires-Dist: pydantic-settings~=2.8.1
Requires-Dist: urllib3~=2.3.0
